{
  "timestamp": "2025-11-07T12:25:05.733475",
  "repositorio_inicializado": false,
  "commit_resultado": {
    "exito": true,
    "archivos_committed": [
      "github_sync_result_20251107_115407.json",
      "mouredev_pro/03_operadores/ejercicios_sesion_03_operadores.py",
      "prompts_master.json",
      "README_Installation.md",
      "README_Prompts.md",
      "README_Voice_Installation.md",
      "Work2027_Ultimate_Guide.md",
      "Work2027_Voice_Guide_Samsung.md",
      "work2027_test_validation.sh",
      "work2027_voice_controller.py"
    ],
    "mensaje_commit": "🚀 Work 2027: 📚 Documentación - 2025-11-07\n\n- - Python: 2 archivos\n- Config: 2 archivos\n- Docs: 5 archivos\n- Scripts: 1 archivos\n\n🤖 Auto-commit by Work 2027 | 12:25:05",
    "hash_commit": "b715f842",
    "error": null
  },
  "push_resultado": {
    "exito": false,
    "branch": "",
    "commits_pushed": 0,
    "error": "No hay repositorio remoto configurado"
  },
  "resumen": "✅ Commit: 10 archivos (b715f842)"
}